humanize/__init__.py
humanize/compat.py
humanize/filesize.py
humanize/i18n.py
humanize/number.py
humanize/time.py
humanize/locale/de_DE/LC_MESSAGES/humanize.mo
humanize/locale/de_DE/LC_MESSAGES/humanize.po
humanize/locale/fr_FR/LC_MESSAGES/humanize.mo
humanize/locale/fr_FR/LC_MESSAGES/humanize.po
humanize/locale/ko_KR/LC_MESSAGES/humanize.mo
humanize/locale/ko_KR/LC_MESSAGES/humanize.po
humanize/locale/nl_NL/LC_MESSAGES/humanize.mo
humanize/locale/nl_NL/LC_MESSAGES/humanize.po
humanize/locale/pt_BR/LC_MESSAGES/humanize.mo
humanize/locale/pt_BR/LC_MESSAGES/humanize.po
humanize/locale/ru_RU/LC_MESSAGES/humanize.mo
humanize/locale/ru_RU/LC_MESSAGES/humanize.po
humanize/locale/sk_SK/LC_MESSAGES/humanize.mo
humanize/locale/sk_SK/LC_MESSAGES/humanize.po
humanize/locale/zh_CN/LC_MESSAGES/humanize.mo
humanize/locale/zh_CN/LC_MESSAGES/humanize.po
humanize_k-0.5.2.dist-info/DESCRIPTION.rst
humanize_k-0.5.2.dist-info/METADATA
humanize_k-0.5.2.dist-info/RECORD
humanize_k-0.5.2.dist-info/WHEEL
humanize_k-0.5.2.dist-info/entry_points.txt
humanize_k-0.5.2.dist-info/metadata.json
humanize_k-0.5.2.dist-info/top_level.txt
